digit_converter.py
digit_converter-2.3.dist-info/LICENSE
digit_converter-2.3.dist-info/METADATA
digit_converter-2.3.dist-info/WHEEL
digit_converter-2.3.dist-info/RECORD
