Metadata-Version: 2.3
Name: digit_converter
Version: 2.3
Summary: A useful tool for digit conversion, applicable in Genetic Algorithms (GA). It transforms a number into a list of digits under any base, for example, `[1, 0, 1, 0, 1, 1, 1, 0] <-> 174`.
License: MIT
Keywords: Digit Converting,Encoding,Genetic Algorithm
Requires-Python: >=3.9,<4.0
Classifier: Intended Audience :: Science/Research
Classifier: License :: OSI Approved :: MIT License
Classifier: License :: Public Domain
Classifier: Natural Language :: English
Classifier: Operating System :: OS Independent
Classifier: Programming Language :: Python
Classifier: Programming Language :: Python :: 3
Classifier: Programming Language :: Python :: 3.9
Classifier: Programming Language :: Python :: 3.10
Classifier: Programming Language :: Python :: 3.11
Classifier: Programming Language :: Python :: 3.12
Classifier: Programming Language :: Python :: 3.13
Classifier: Topic :: Scientific/Engineering :: Mathematics
Project-URL: Homepage, https://github.com/Freakwill/digit-converter
Project-URL: Repository, https://github.com/Freakwill/digit-converter
